[
  {"text": "CalFresh", "label": "ORG"},
  {"text": "Calfresh", "label": "ORG"},
  {"text": "calfresh", "label": "ORG"},
  {"text": "Cal Fresh", "label": "ORG"},
  {"text": "cal fresh", "label": "ORG"},
  {"text": "sar7", "label": "ORG"},
  {"text": "SAR 7", "label": "ORG"},
  {"text": "sar 7", "label": "ORG"},
  {"text": "sar", "label": "ORG"},
  {"text": "SR7", "label": "ORG"},
  {"text": "SR 7", "label": "ORG"},
  {"text": "sr 7", "label": "ORG"},
  {"text": "sr7", "label": "ORG"},
  {"text": "Covered GPE",  "label": "ORG"},
  {"text": "Covered California", "label": "ORG"},
  {"text": "medi-cal", "label": "ORG"},
  {"text": "Medi-Cal", "label": "ORG"},
  {"text": "Medi-cal", "label": "ORG"},
  {"text": "Medical", "label": "ORG"},
  {"text": "medical", "label": "ORG"},
  {"text": "USC", "label": "ORG"},
  {"text": "EOPS", "label": "ORG"},
  {"text": "SSDI", "label": "ORG"},
  {"text": "Social Security Disability", "label": "ORG"},
  {"text": "ab12", "label": "ORG"},
  {"text": "SSI", "label": "ORG"},
  {"text": "FAFSA", "label": "ORG"},
  {"text": "EOP", "label": "ORG"},
  {"text": "SS#", "label": "ORG"},
  {"text": "ss#", "label": "ORG"},
  {"text": "ssi", "label": "ORG"},
  {"text": "ssdi", "label": "ORG"},
  {"text": "SSI", "label": "ORG"},
  {"text": "SDI", "label": "ORG"},
  {"text": "SSDI", "label": "ORG"},
  {"text": "pfl", "label": "OTHER"},
  {"text": "DV", "label": "OTHER"},
  {"text": "D.O.B.", "label": "DATE"},
  {"text": "food stamps", "label": "ORG"},
  {"text": "Food Stamps", "label": "ORG"},
  {"text": "foodstamps", "label": "ORG"},
  {"text": "foodstamp", "label": "ORG"},
  {"text": "Foodstamps", "label": "ORG"},
  {"text": "cash aid", "label": "ORG"},
  {"text": "FRC", "label": "ORG"},
  {"text": "Financial Aid", "label": "ORG"},
  {"text": "FoodCorps", "label": "ORG"},
  {"text": "WIC", "label": "ORG"},
  {"text": "wic", "label": "ORG"},
  {"text": "SLEs", "label": "ORG"},
  {"text": "UI", "label": "ORG"}
]
